g42cloudsdkcce/__init__.py
g42cloudsdkcce/v3/__init__.py
g42cloudsdkcce/v3/cce_async_client.py
g42cloudsdkcce/v3/cce_client.py
g42cloudsdkcce/v3/model/__init__.py
g42cloudsdkcce/v3/model/addon_instance.py
g42cloudsdkcce/v3/model/addon_instance_status.py
g42cloudsdkcce/v3/model/addon_template.py
g42cloudsdkcce/v3/model/authenticating_proxy.py
g42cloudsdkcce/v3/model/authentication.py
g42cloudsdkcce/v3/model/awake_cluster_request.py
g42cloudsdkcce/v3/model/awake_cluster_response.py
g42cloudsdkcce/v3/model/cert_duration.py
g42cloudsdkcce/v3/model/cluster.py
g42cloudsdkcce/v3/model/cluster_cert.py
g42cloudsdkcce/v3/model/cluster_endpoints.py
g42cloudsdkcce/v3/model/cluster_extend_param.py
g42cloudsdkcce/v3/model/cluster_information.py
g42cloudsdkcce/v3/model/cluster_information_spec.py
g42cloudsdkcce/v3/model/cluster_metadata.py
g42cloudsdkcce/v3/model/cluster_node_information.py
g42cloudsdkcce/v3/model/cluster_node_information_metadata.py
g42cloudsdkcce/v3/model/cluster_spec.py
g42cloudsdkcce/v3/model/cluster_status.py
g42cloudsdkcce/v3/model/clusters.py
g42cloudsdkcce/v3/model/container_cidr.py
g42cloudsdkcce/v3/model/container_network.py
g42cloudsdkcce/v3/model/container_network_update.py
g42cloudsdkcce/v3/model/context.py
g42cloudsdkcce/v3/model/contexts.py
g42cloudsdkcce/v3/model/create_addon_instance_request.py
g42cloudsdkcce/v3/model/create_addon_instance_response.py
g42cloudsdkcce/v3/model/create_cloud_persistent_volume_claims_request.py
g42cloudsdkcce/v3/model/create_cloud_persistent_volume_claims_response.py
g42cloudsdkcce/v3/model/create_cluster_request.py
g42cloudsdkcce/v3/model/create_cluster_response.py
g42cloudsdkcce/v3/model/create_kubernetes_cluster_cert_request.py
g42cloudsdkcce/v3/model/create_kubernetes_cluster_cert_response.py
g42cloudsdkcce/v3/model/create_node_pool_request.py
g42cloudsdkcce/v3/model/create_node_pool_response.py
g42cloudsdkcce/v3/model/create_node_request.py
g42cloudsdkcce/v3/model/create_node_response.py
g42cloudsdkcce-0.0.10b0.dist-info/LICENSE
g42cloudsdkcce-0.0.10b0.dist-info/METADATA
g42cloudsdkcce-0.0.10b0.dist-info/WHEEL
g42cloudsdkcce-0.0.10b0.dist-info/top_level.txt
g42cloudsdkcce-0.0.10b0.dist-info/RECORD
